nclearn/__init__.py
nclearn/dl.py
nclearn/example.py
nclearn/ml.py
nclearn-0.0.1.dist-info/LICENSE
nclearn-0.0.1.dist-info/METADATA
nclearn-0.0.1.dist-info/WHEEL
nclearn-0.0.1.dist-info/top_level.txt
nclearn-0.0.1.dist-info/RECORD
