Metadata-Version: 2.1
Name: nclearn
Version: 0.0.1
Summary: A personal scikit-learn like library to practice ml algorithms and software development
Home-page: https://github.com/NecmettinCeylan/nclearn
Author: Necmettin Ceylan
Author-email: necmettinceylan@hotmail.com
License: UNKNOWN
Project-URL: Bug Tracker, https://github.com/NecmettinCeylan/nclearn/issues
Platform: UNKNOWN
Classifier: Programming Language :: Python :: 3
Classifier: License :: OSI Approved :: MIT License
Classifier: Operating System :: OS Independent
Requires-Python: >=3.6
License-File: LICENSE
